pynuspell.cpython-38-x86_64-linux-gnu.so
pynuspell/__init__.pyi
pynuspell-1.0.0.dist-info/RECORD
pynuspell-1.0.0.dist-info/METADATA
pynuspell-1.0.0.dist-info/top_level.txt
pynuspell-1.0.0.dist-info/WHEEL
pynuspell-1.0.0.dist-info/LICENSE
