Metadata-Version: 2.1
Name: pynuspell
Version: 1.0.0
Summary: Python bidings for Nuspell - a fast and safe spellcheckingC++ library
Home-page: https://github.com/scherzocrk/pynuspell
Author: Renan Santos
Author-email: renan.engmec@gmail.com
License: LGPL-3.0
Platform: UNKNOWN
Classifier: License :: OSI Approved :: GNU Lesser General Public License v3 (LGPLv3)
Classifier: Programming Language :: Python :: 3 :: Only
Classifier: Programming Language :: Python :: 3
Classifier: Programming Language :: Python :: 3.6
Classifier: Programming Language :: Python :: 3.7
Classifier: Programming Language :: Python :: 3.8
Classifier: Programming Language :: Python :: 3.9
Classifier: Programming Language :: C++
License-File: LICENSE
